CHANGES.txt
CONTRIBUTORS.txt
MANIFEST.in
README.rst
README.txt
setup.py
docs/LICENSE.txt
src/collective/__init__.py
src/collective.backtowork.egg-info/PKG-INFO
src/collective.backtowork.egg-info/SOURCES.txt
src/collective.backtowork.egg-info/dependency_links.txt
src/collective.backtowork.egg-info/entry_points.txt
src/collective.backtowork.egg-info/namespace_packages.txt
src/collective.backtowork.egg-info/not-zip-safe
src/collective.backtowork.egg-info/requires.txt
src/collective.backtowork.egg-info/top_level.txt
src/collective/backtowork/__init__.py
src/collective/backtowork/configure.zcml