Metadata-Version: 1.0
Name: collective.backtowork
Version: 0.6.3
Summary: A little event handler to notify you that zope is up and running
Home-page: http://github.com/collective/
Author: Patrick Gerken
Author-email: do3cc@do3.cc
License: BSD
Platform: UNKNOWN
Classifier: Programming Language :: Python
